setup.py
Driver_zch.egg-info/PKG-INFO
Driver_zch.egg-info/SOURCES.txt
Driver_zch.egg-info/dependency_links.txt
Driver_zch.egg-info/requires.txt
Driver_zch.egg-info/top_level.txt
scripts/can_logger.py
scripts/can_player.py
scripts/can_viewer.py
zhouch23/__init__.py
zhouch23/bit_timing.py
zhouch23/broadcastmanager.py
zhouch23/bus.py
zhouch23/ctypesutil.py
zhouch23/interface.py
zhouch23/listener.py
zhouch23/logger.py
zhouch23/message.py
zhouch23/notifier.py
zhouch23/player.py
zhouch23/thread_safe_bus.py
zhouch23/typechecking.py
zhouch23/util.py
zhouch23/viewer.py
zhouch23/interfaces/__init__.py
zhouch23/interfaces/canalystii.py
zhouch23/interfaces/iscan.py
zhouch23/interfaces/nican.py
zhouch23/interfaces/robotell.py
zhouch23/interfaces/slcan.py
zhouch23/interfaces/virtual.py
zhouch23/interfaces/vector/__init__.py
zhouch23/interfaces/vector/canlib.py
zhouch23/interfaces/vector/exceptions.py
zhouch23/interfaces/vector/xlclass.py
zhouch23/interfaces/vector/xldefine.py
zhouch23/interfaces/vector/xldriver.py
zhouch23/io/__init__.py
zhouch23/io/asc.py
zhouch23/io/blf.py
zhouch23/io/canutils.py
zhouch23/io/csv.py
zhouch23/io/generic.py
zhouch23/io/logger.py
zhouch23/io/player.py
zhouch23/io/printer.py
zhouch23/io/sqlite.py